aenum/CHANGES
aenum/LICENSE
aenum/__init__.py
aenum/_common.py
aenum/_constant.py
aenum/_enum.py
aenum/_py2.py
aenum/_tuple.py
aenum/test.py
aenum/test_v37.py
aenum/doc/aenum.pdf
aenum/doc/aenum.rst
aenum-3.1.14.dist-info/METADATA
aenum-3.1.14.dist-info/WHEEL
aenum-3.1.14.dist-info/top_level.txt
aenum-3.1.14.dist-info/RECORD
